ecgai_ai_training/__init__.py
ecgai_ai_training/ecg_loader.py
ecgai_ai_training/ecg_trainer.py
ecgai_ai_training/ecg_trainer_builder.py
ecgai_ai_training/images.py
ecgai_ai_training/model_base.py
ecgai_ai_training/model_factory.py
ecgai_ai_training/models.py
ecgai_ai_training/neural_cbam.py
ecgai_ai_training/neural_losses.py
ecgai_ai_training/neural_models.py
ecgai_ai_training/service.py
ecgai_ai_training-0.1.10.dist-info/LICENSE
ecgai_ai_training-0.1.10.dist-info/WHEEL
ecgai_ai_training-0.1.10.dist-info/METADATA
ecgai_ai_training-0.1.10.dist-info/RECORD
