Metadata-Version: 2.1
Name: ecgai-ai-training
Version: 0.1.10
Summary: 
Author: RobC
Author-email: rob.clapham@gmail.com
Requires-Python: >=3.7.1,<3.11
Classifier: Programming Language :: Python :: 3
Classifier: Programming Language :: Python :: 3.8
Classifier: Programming Language :: Python :: 3.9
Classifier: Programming Language :: Python :: 3.10
Requires-Dist: PyWavelets (==1.3.0)
Requires-Dist: adabound (>=0.0.5,<0.0.6)
Requires-Dist: numpy (==1.21.6)
Requires-Dist: pandas (==1.3.5)
Requires-Dist: pydantic (>=1.10.2,<2.0.0)
Requires-Dist: pytest (>=7.2.0,<8.0.0)
Requires-Dist: scikit-image (==0.18.3)
Requires-Dist: scikit-learn (==1.0.2)
Requires-Dist: torch (==1.12.1)
